{
  "openapi": "3.0.1",
  "info": {
    "title": "Backend",
    "version": "1.0"
  },
  "paths": {
    "/api/Account/index": {
      "get": {
        "tags": [
          "Account"
        ],
        "responses": {
          "200": {
            "description": "OK"
          }
        }
      }
    },
    "/api/Account/register": {
      "post": {
        "tags": [
          "Account"
        ],
        "requestBody": {
          "content": {
            "application/json": {
              "schema": {
                "$ref": "#/components/schemas/RegisterAccountDTO"
              }
            },
            "text/json": {
              "schema": {
                "$ref": "#/components/schemas/RegisterAccountDTO"
              }
            },
            "application/*+json": {
              "schema": {
                "$ref": "#/components/schemas/RegisterAccountDTO"
              }
            }
          }
        },
        "responses": {
          "200": {
            "description": "OK"
          }
        }
      }
    },
    "/api/Account/login": {
      "post": {
        "tags": [
          "Account"
        ],
        "requestBody": {
          "content": {
            "application/json": {
              "schema": {
                "$ref": "#/components/schemas/LoginAccountDTO"
              }
            },
            "text/json": {
              "schema": {
                "$ref": "#/components/schemas/LoginAccountDTO"
              }
            },
            "application/*+json": {
              "schema": {
                "$ref": "#/components/schemas/LoginAccountDTO"
              }
            }
          }
        },
        "responses": {
          "200": {
            "description": "OK"
          }
        }
      }
    },
    "/api/Account/users/me": {
      "get": {
        "tags": [
          "Account"
        ],
        "responses": {
          "200": {
            "description": "OK"
          }
        }
      }
    },
    "/api/Tasks/index": {
      "get": {
        "tags": [
          "Tasks"
        ],
        "responses": {
          "200": {
            "description": "OK"
          }
        }
      }
    },
    "/api/Tasks/add": {
      "post": {
        "tags": [
          "Tasks"
        ],
        "requestBody": {
          "content": {
            "application/json": {
              "schema": {
                "$ref": "#/components/schemas/TaskAddDTO"
              }
            },
            "text/json": {
              "schema": {
                "$ref": "#/components/schemas/TaskAddDTO"
              }
            },
            "application/*+json": {
              "schema": {
                "$ref": "#/components/schemas/TaskAddDTO"
              }
            }
          }
        },
        "responses": {
          "200": {
            "description": "OK"
          }
        }
      }
    },
    "/api/Tasks/get": {
      "get": {
        "tags": [
          "Tasks"
        ],
        "responses": {
          "200": {
            "description": "OK"
          }
        }
      }
    },
    "/api/Tasks/nextDl": {
      "get": {
        "tags": [
          "Tasks"
        ],
        "responses": {
          "200": {
            "description": "OK"
          }
        }
      }
    },
    "/api/Tasks/getFiveDl": {
      "get": {
        "tags": [
          "Tasks"
        ],
        "responses": {
          "200": {
            "description": "OK"
          }
        }
      }
    },
    "/api/Tasks/overdue": {
      "get": {
        "tags": [
          "Tasks"
        ],
        "responses": {
          "200": {
            "description": "OK"
          }
        }
      }
    }
  },
  "components": {
    "schemas": {
      "LoginAccountDTO": {
        "type": "object",
        "properties": {
          "email": {
            "type": "string",
            "nullable": true
          },
          "password": {
            "type": "string",
            "nullable": true
          }
        },
        "additionalProperties": false
      },
      "RegisterAccountDTO": {
        "type": "object",
        "properties": {
          "username": {
            "type": "string",
            "nullable": true
          },
          "password": {
            "type": "string",
            "nullable": true
          },
          "email": {
            "type": "string",
            "nullable": true
          }
        },
        "additionalProperties": false
      },
      "TaskAddDTO": {
        "type": "object",
        "properties": {
          "title": {
            "type": "string",
            "nullable": true
          },
          "description": {
            "type": "string",
            "nullable": true
          },
          "deadline": {
            "type": "string",
            "format": "date-time"
          }
        },
        "additionalProperties": false
      }
    },
    "securitySchemes": {
      "Bearer": {
        "type": "http",
        "description": "Put **_ONLY_** your JWT Bearer token on textbox below!",
        "scheme": "Bearer",
        "bearerFormat": "JWT"
      }
    }
  },
  "security": [
    {
      "Bearer": [ ]
    }
  ]
}